apitelematel_client/__init__.py
apitelematel_client/client.py
apitelematel_client/config.py
apitelematel_client/exceptions.py
apitelematel_client-0.1.6.dist-info/METADATA
apitelematel_client-0.1.6.dist-info/WHEEL
apitelematel_client-0.1.6.dist-info/top_level.txt
apitelematel_client-0.1.6.dist-info/RECORD
