Metadata-Version: 2.4
Name: apitelematel-client
Version: 0.1.6
Summary: Cliente ligero para consumir la API de apitelematel desde otras aplicaciones
Requires-Python: >=3.10
Requires-Dist: requests>=2.28
Requires-Dist: python-dotenv>=1.0
